sensebook/__init__.py
sensebook/_abc.py
sensebook/_login.py
sensebook/_pull_handler.py
sensebook/_utils.py
sensebook-0.2.0.dist-info/LICENSE.txt
sensebook-0.2.0.dist-info/WHEEL
sensebook-0.2.0.dist-info/METADATA
sensebook-0.2.0.dist-info/RECORD
