Metadata-Version: 2.1
Name: sensebook
Version: 0.2.0
Summary: Making sense of Facebooks undocumented API.
Home-page: https://github.com/madsmtm/sensebook/
License: BSD 3-Clause
Keywords: Facebook FB Messenger Library Documentation Sans-IO
Author: Mads Marquart
Author-email: madsmtm@gmail.com
Requires-Python: >=3.5, <4.0
Classifier: Development Status :: 1 - Planning
Classifier: Intended Audience :: Developers
Classifier: Intended Audience :: Information Technology
Classifier: License :: OSI Approved :: BSD License
Classifier: Operating System :: OS Independent
Classifier: Natural Language :: English
Classifier: Programming Language :: JavaScript
Classifier: Programming Language :: Python
Classifier: Programming Language :: Python :: 3
Classifier: Programming Language :: Python :: 3 :: Only
Classifier: Programming Language :: Python :: 3.5
Classifier: Programming Language :: Python :: 3.6
Classifier: Programming Language :: Python :: 3.7
Classifier: Programming Language :: Python :: Implementation :: CPython
Classifier: Programming Language :: Python :: Implementation :: PyPy
Classifier: Topic :: Communications :: Chat
Classifier: Topic :: Documentation
Classifier: Topic :: Internet :: WWW/HTTP
Classifier: Topic :: Internet :: WWW/HTTP :: Dynamic Content
Classifier: Topic :: Software Development :: Libraries
Classifier: Topic :: Software Development :: Libraries :: Python Modules
Requires-Dist: attrs>=18.2.0
Requires-Dist: beautifulsoup4
Requires-Dist: black; extra == "dev"
Requires-Dist: requests; extra == "sync"
Requires-Dist: pytest; extra == "test"
Requires-Dist: pytest-mock; extra == "test"
Requires-Dist: pytest-raises; extra == "test"
Requires-Dist: pytest-travis-fold; extra == "test"
Project-URL: Repository, https://github.com/madsmtm/sensebook/
Provides-Extra: dev
Provides-Extra: sync
Provides-Extra: test
